flask_casbin_redis_watcher/__init__.py
flask_casbin_redis_watcher/watcher.py
flask_casbin_redis_watcher-0.1.0.dist-info/LICENSE.txt
flask_casbin_redis_watcher-0.1.0.dist-info/METADATA
flask_casbin_redis_watcher-0.1.0.dist-info/WHEEL
flask_casbin_redis_watcher-0.1.0.dist-info/top_level.txt
flask_casbin_redis_watcher-0.1.0.dist-info/RECORD
