Metadata-Version: 2.1
Name: flask-casbin-redis-watcher
Version: 0.1.0
Summary: flask-casbin-redis-watcher
Home-page: https://github.com/sciencelogic/flask-casbin-redis-watcher
Author: ScienceLogic
License: Apache2
Download-URL: https://github.com/sciencelogic/flask-casbin-redis-watcher/tarball/0.1.0
Keywords: pycasbin,casbin,flask,rbac
Platform: UNKNOWN
Classifier: Development Status :: 3 - Alpha
Classifier: Intended Audience :: Developers
Classifier: Programming Language :: Python :: 3
Requires-Python: >3.5
Requires-Dist: redis
Requires-Dist: flask-casbin (==0.1.1)
